aitoolkit_cam/__init__.py
aitoolkit_cam/camera.py
aitoolkit_cam/config.py
aitoolkit_cam/core.py
aitoolkit_cam/device_manager.py
aitoolkit_cam/fastapi_adapter.py
aitoolkit_cam/filters.py
aitoolkit_cam/frame_buffer.py
aitoolkit_cam/hub.py
aitoolkit_cam/video_blueprint.py
aitoolkit_cam-3.5.0.dist-info/licenses/LICENSE
aitoolkit_cam-3.5.0.dist-info/METADATA
aitoolkit_cam-3.5.0.dist-info/WHEEL
aitoolkit_cam-3.5.0.dist-info/top_level.txt
aitoolkit_cam-3.5.0.dist-info/RECORD
