Metadata-Version: 2.4
Name: aitoolkit-cam
Version: 3.5.0
Summary: ARM摄像头工具包 v3.0 - 专为Jupyter环境和ARM设备优化，修复MJPEG流问题
Home-page: https://github.com/dianx12/aitoolkit-cam
Author: Haitao Wang
Author-email: dianx12@163.com
Project-URL: Bug Reports, https://github.com/dianx12/aitoolkit-cam/issues
Project-URL: Source, https://github.com/dianx12/aitoolkit-cam
Project-URL: Documentation, https://github.com/dianx12/aitoolkit-cam/blob/main/README.md
Keywords: camera opencv arm jupyter fastapi mjpeg streaming
Classifier: Development Status :: 4 - Beta
Classifier: Intended Audience :: Developers
Classifier: License :: OSI Approved :: MIT License
Classifier: Programming Language :: Python :: 3
Classifier: Programming Language :: Python :: 3.8
Classifier: Programming Language :: Python :: 3.9
Classifier: Programming Language :: Python :: 3.10
Classifier: Programming Language :: Python :: 3.11
Classifier: Programming Language :: Python :: 3.12
Classifier: Topic :: Multimedia :: Video :: Capture
Classifier: Topic :: Scientific/Engineering :: Image Processing
Requires-Python: >=3.8
License-File: LICENSE
Requires-Dist: opencv-python-headless>=4.5.0
Requires-Dist: numpy>=1.19.0
Requires-Dist: fastapi>=0.68.0
Requires-Dist: uvicorn>=0.15.0
Provides-Extra: dev
Requires-Dist: pytest>=6.0; extra == "dev"
Requires-Dist: pytest-cov>=2.0; extra == "dev"
Requires-Dist: black>=21.0; extra == "dev"
Requires-Dist: flake8>=3.8; extra == "dev"
Provides-Extra: jupyter
Requires-Dist: jupyter>=1.0.0; extra == "jupyter"
Requires-Dist: ipython>=7.0.0; extra == "jupyter"
Requires-Dist: matplotlib>=3.3.0; extra == "jupyter"
Dynamic: author
Dynamic: author-email
Dynamic: classifier
Dynamic: description
Dynamic: description-content-type
Dynamic: home-page
Dynamic: keywords
Dynamic: license-file
Dynamic: project-url
Dynamic: provides-extra
Dynamic: requires-dist
Dynamic: requires-python
Dynamic: summary
